leonidig_lib/__init__.py
leonidig_lib/core.py
leonidig123lb-1.1.dist-info/METADATA
leonidig123lb-1.1.dist-info/WHEEL
leonidig123lb-1.1.dist-info/top_level.txt
leonidig123lb-1.1.dist-info/RECORD
