Metadata-Version: 2.4
Name: leonidig123lb
Version: 1.1
Summary: Test Library
Author: leonidig
Author-email: leonid200955@gmail.com
Requires-Python: >=3.12
Dynamic: author
Dynamic: author-email
Dynamic: requires-python
Dynamic: summary
